{
  "fill" : "system-light",
  "groups" : [
    {
      "blur-material" : 0.5,
      "hidden" : false,
      "layers" : [
        {
          "glass" : true,
          "hidden" : false,
          "image-name" : "demorunnerplay.svg",
          "name" : "demorunnerplay",
          "opacity" : 1
        }
      ],
      "opacity" : 1,
      "shadow" : {
        "kind" : "neutral",
        "opacity" : 0.5
      },
      "specular" : true,
      "translucency" : {
        "enabled" : true,
        "value" : 0.6
      }
    },
    {
      "blur-material" : null,
      "layers" : [
        {
          "hidden" : false,
          "image-name" : "demorunnerbg.svg",
          "name" : "demorunnerbg"
        }
      ],
      "shadow" : {
        "kind" : "neutral",
        "opacity" : 0.5
      },
      "specular" : true,
      "translucency" : {
        "enabled" : false,
        "value" : 0
      }
    }
  ],
  "supported-platforms" : {
    "squares" : "shared"
  }
}